bioaug/CutMix.py
bioaug/Distortion.py
bioaug/Drift.py
bioaug/GaussianNoise.py
bioaug/ImpedanceVariation.py
bioaug/LocalJittering.py
bioaug/MagnitudeWarping.py
bioaug/MixUp.py
bioaug/Permutation.py
bioaug/RandomCutout.py
bioaug/Scaling.py
bioaug/TimeWarping.py
bioaug/__init__.py
bioaug/uLawNormalization.py
bioaug-0.1.4.dist-info/METADATA
bioaug-0.1.4.dist-info/WHEEL
bioaug-0.1.4.dist-info/top_level.txt
bioaug-0.1.4.dist-info/RECORD
