Metadata-Version: 2.1
Name: bioaug
Version: 0.1.4
Summary: A toolbox for biosignal augmentation written in Python
Home-page: https://github.com/peijii/BioAug
Author: Peiji Chen
Author-email: peijichen0324@gmail.com
Classifier: Programming Language :: Python :: 3
Classifier: License :: OSI Approved :: MIT License
Classifier: Operating System :: OS Independent
Requires-Python: >=3.8
Requires-Dist: numpy
Requires-Dist: pandas
Requires-Dist: matplotlib
Requires-Dist: scipy
